grafana_api/__init__.py
grafana_api/admin.py
grafana_api/alerting.py
grafana_api/alerting_notifications.py
grafana_api/alerting_provisioning.py
grafana_api/annotations.py
grafana_api/api.py
grafana_api/authentication.py
grafana_api/correlations.py
grafana_api/dashboard.py
grafana_api/datasource.py
grafana_api/external_group.py
grafana_api/folder.py
grafana_api/legacy_alerting.py
grafana_api/legacy_playlist.py
grafana_api/library.py
grafana_api/licensing.py
grafana_api/model.py
grafana_api/organisation.py
grafana_api/other_http.py
grafana_api/playlist.py
grafana_api/preferences.py
grafana_api/query_history.py
grafana_api/rbac.py
grafana_api/reporting.py
grafana_api/search.py
grafana_api/service_account.py
grafana_api/short_url.py
grafana_api/snapshot.py
grafana_api/sso_settings.py
grafana_api/team.py
grafana_api/user.py
grafana_api_sdk-0.8.0.dist-info/LICENSE
grafana_api_sdk-0.8.0.dist-info/METADATA
grafana_api_sdk-0.8.0.dist-info/WHEEL
grafana_api_sdk-0.8.0.dist-info/top_level.txt
grafana_api_sdk-0.8.0.dist-info/RECORD
