Metadata-Version: 2.2
Name: grafana-api-sdk
Version: 0.8.0
Summary: A Grafana API SDK
Home-page: https://github.com/ZPascal/grafana_api_sdk
Author: Pascal Zimmermann
Author-email: info@theiotstudio.com
License: Apache-2.0 License
Project-URL: Source, https://github.com/ZPascal/grafana_api_sdk
Project-URL: Bug Tracker, https://github.com/ZPascal/grafana_api_sdk/issues
Project-URL: Documentation, https://zpascal.github.io/grafana_api_sdk/
Classifier: Programming Language :: Python :: 3
Classifier: License :: OSI Approved
Classifier: Operating System :: OS Independent
Requires-Python: >=3.8
License-File: LICENSE
Requires-Dist: httpx
Provides-Extra: http2
Requires-Dist: httpx[http2]; extra == "http2"
Dynamic: author
Dynamic: author-email
Dynamic: classifier
Dynamic: description
Dynamic: description-content-type
Dynamic: home-page
Dynamic: license
Dynamic: project-url
Dynamic: provides-extra
Dynamic: requires-dist
Dynamic: requires-python
Dynamic: summary
